api/__init__.py
gal/__init__.py
gal/core/__init__.py
gal/core/aggregator.py
gal/core/communicate_client.py
gal/core/communicate_server.py
gal/core/job_manager.py
gal/core/server.py
gal/core/strategy.py
gal/core/trainer.py
gal/core/trainer_controller.py
gal/entity/__init__.py
gal/entity/job.py
gal/entity/runtime_config.py
gal/exceptions/__init__.py
gal/exceptions/fl_expection.py
gal/lib/__init__.py
gal/utils/__init__.py
gal/utils/utils.py
gl/__init__.py
gl/core/__init__.py
gl/core/aggregator.py
gl/core/communicate_client.py
gl/core/communicate_server.py
gl/core/job_manager.py
gl/core/server.py
gl/core/strategy.py
gl/core/trainer.py
gl/core/trainer_controller.py
gl/entity/__init__.py
gl/entity/job.py
gl/entity/runtime_config.py
gl/exceptions/__init__.py
gl/exceptions/fl_expection.py
gl/lib/__init__.py
gl/utils/__init__.py
gl/utils/utils.py
gal-0.1.0.dist-info/LICENSE
gal-0.1.0.dist-info/METADATA
gal-0.1.0.dist-info/WHEEL
gal-0.1.0.dist-info/top_level.txt
gal-0.1.0.dist-info/zip-safe
gal-0.1.0.dist-info/RECORD
